CHANGELOG.md
docs/algorithm.md
docs/clustering.ipynb
docs/development.md
docs/parameters.md
docs/stitching-api.md
docs/time-series.ipynb
docs/tutorial.ipynb
example_simple.py
syndiffix/__init__.py
syndiffix/anonymizer.py
syndiffix/blob.py
syndiffix/bucket.py
syndiffix/clustering/__init__.py
syndiffix/clustering/common.py
syndiffix/clustering/features.py
syndiffix/clustering/measures.py
syndiffix/clustering/sampling.py
syndiffix/clustering/solver.py
syndiffix/clustering/stitching.py
syndiffix/clustering/strategy.py
syndiffix/common.py
syndiffix/counters.py
syndiffix/forest.py
syndiffix/interval.py
syndiffix/microdata.py
syndiffix/stitcher.py
syndiffix/synthesizer.py
syndiffix/tree.py
syndiffix-1.0.8.dist-info/LICENSE.md
syndiffix-1.0.8.dist-info/METADATA
syndiffix-1.0.8.dist-info/WHEEL
syndiffix-1.0.8.dist-info/RECORD
