Metadata-Version: 2.1
Name: syndiffix
Version: 1.0.8
Summary: Python implementation of the SynDiffix synthetic data generation mechanism.
Home-page: https://open-diffix.org/
License: MIT
Author: Open Diffix
Author-email: hello@open-diffix.org
Requires-Python: >=3.10
Classifier: License :: OSI Approved :: MIT License
Classifier: Programming Language :: Python :: 3
Classifier: Programming Language :: Python :: 3.10
Classifier: Programming Language :: Python :: 3.11
Requires-Dist: appdirs (>=1.4.4)
Requires-Dist: fastparquet (>=2024.5.0)
Requires-Dist: flake8-pyproject (>=1.2.3)
Requires-Dist: pandas (>=2.1)
Requires-Dist: pyarrow (>=17.0.0)
Requires-Dist: scikit-learn (>=1.3)
Requires-Dist: scipy (>=1.9)
Requires-Dist: types-appdirs (>=1.4.3.5)
Project-URL: Repository, https://github.com/diffix/syndiffix
